README.md
setup.cfg
setup.py
pyupdate/__init__.py
pyupdate/self.py
pyupdate.egg-info/PKG-INFO
pyupdate.egg-info/SOURCES.txt
pyupdate.egg-info/dependency_links.txt
pyupdate.egg-info/requires.txt
pyupdate.egg-info/top_level.txt
pyupdate/ha_custom/__init__.py
pyupdate/ha_custom/common.py
pyupdate/ha_custom/custom_cards.py
pyupdate/ha_custom/custom_components.py
pyupdate/ha_custom/python_scripts.py