Metadata-Version: 2.1
Name: pyupdate
Version: 0.2.16
Summary: A python package to update stuff.
Home-page: https://github.com/ludeeus/pyupdate
Author: Joakim Sorensen
Author-email: ludeeus@gmail.com
License: UNKNOWN
Platform: UNKNOWN
Classifier: Programming Language :: Python :: 3
Classifier: License :: OSI Approved :: MIT License
Classifier: Operating System :: OS Independent
